wixok/__init__.py
wixok/folder.py
wixok_folder-25.8.2.dist-info/licenses/LICENSE
wixok_folder-25.8.2.dist-info/METADATA
wixok_folder-25.8.2.dist-info/WHEEL
wixok_folder-25.8.2.dist-info/entry_points.txt
wixok_folder-25.8.2.dist-info/top_level.txt
wixok_folder-25.8.2.dist-info/RECORD
