Metadata-Version: 2.4
Name: wixok.folder
Version: 25.8.2
Summary: Simple Python package for folder operations.
Author-email: Wixok <contact@wixok.com>
Maintainer-email: Mohammed Dellihr <mohammeddellihr@maildoo.com>
License: The MIT License (MIT)
Project-URL: Repository, https://github.com/wixok/folder
Project-URL: Issues, https://github.com/wixok/folder/issues
Keywords: folder,folders,folder-management
Classifier: License :: OSI Approved :: MIT License
Classifier: Programming Language :: Python :: 3
Requires-Python: >=3.8
License-File: LICENSE
Provides-Extra: dev
Requires-Dist: pytest; extra == "dev"
Dynamic: license-file
